{
  "version": "kc-mission-v1",
  "name": "platform-kind",
  "missionClass": "install",
  "author": "KubeStellar Bot",
  "authorGithub": "kubestellar",
  "mission": {
    "title": "Install and Configure Kind (Kubernetes in Docker)",
    "description": "Kind (Kubernetes in Docker) is a tool for running local Kubernetes clusters using Docker container nodes. It is primarily designed for testing Kubernetes itself but can also be used for local development or CI. The key trade-off is that it requires Docker to be installed and may not be suitable for production environments.",
    "type": "deploy",
    "status": "completed",
    "estimatedMinutes": 15,
    "steps": [
      {
        "title": "Install Docker",
        "description": "Kind requires Docker to create and manage Kubernetes clusters. Ensure Docker is installed and running on your machine.\n\n```bash\n\nsudo apt-get update && sudo apt-get install -y docker.io\n\nbrew install --cask docker\n\n```\n\n> For Ubuntu/Debian systems.\n> For macOS users.",
        "commands": [
          "sudo apt-get update && sudo apt-get install -y docker.io",
          "brew install --cask docker"
        ]
      },
      {
        "title": "Download and Install Kind",
        "description": "This step installs Kind by downloading the binary for your platform and placing it in your PATH.\n\n```bash\n\n[ $(uname -m) = x86_64 ] && curl -Lo ./kind https://kind.sigs.k8s.io/dl/v0.31.0/kind-$(uname)-amd64 && chmod +x ./kind && sudo mv ./kind /usr/local/bin/kind\n\n[ $(uname -m) = aarch64 ] && curl -Lo ./kind https://kind.sigs.k8s.io/dl/v0.31.0/kind-$(uname)-arm64 && chmod +x ./kind && sudo mv ./kind /usr/local/bin/kind\n\n```\n\n> For AMD64 / x86_64 on Linux.\n> For ARM64 on Linux.",
        "commands": [
          "[ $(uname -m) = x86_64 ] && curl -Lo ./kind https://kind.sigs.k8s.io/dl/v0.31.0/kind-$(uname)-amd64 && chmod +x ./kind && sudo mv ./kind /usr/local/bin/kind",
          "[ $(uname -m) = aarch64 ] && curl -Lo ./kind https://kind.sigs.k8s.io/dl/v0.31.0/kind-$(uname)-arm64 && chmod +x ./kind && sudo mv ./kind /usr/local/bin/kind"
        ]
      },
      {
        "title": "Create a Kubernetes Cluster",
        "description": "This command creates a local Kubernetes cluster using Kind with the default configuration.\n\n```bash\n\nkind create cluster --image kindest/node:v1.31.0\n\n```\n\n> This creates a cluster with Kubernetes version 1.31.",
        "commands": [
          "kind create cluster --image kindest/node:v1.31.0"
        ]
      },
      {
        "title": "Verify the Cluster",
        "description": "Check that the cluster is up and running by listing the nodes.\n\n```bash\n\nkubectl get nodes\n\n```\n\n> You should see the nodes listed with their status.",
        "commands": [
          "kubectl get nodes"
        ]
      }
    ],
    "uninstall": [
      {
        "title": "Remove the Kind Cluster",
        "description": "This command deletes the Kind cluster and all associated resources. Be aware that any data stored in the cluster will be lost.\n\n```bash\n\nkind delete cluster\n\n```\n\n> This will remove the cluster and all its resources.",
        "commands": [
          "kind delete cluster"
        ]
      },
      {
        "title": "Remove Kind Binary",
        "description": "This command removes the Kind binary from your system.\n\n```bash\n\nsudo rm /usr/local/bin/kind\n\n```\n\n> This will delete the Kind executable.",
        "commands": [
          "sudo rm /usr/local/bin/kind"
        ]
      }
    ],
    "upgrade": [
      {
        "title": "Upgrade Kind",
        "description": "Before upgrading, ensure you have a backup of any important data. Then, upgrade Kind to the latest version.\n\n```bash\n\ncurl -Lo ./kind https://kind.sigs.k8s.io/dl/v0.31.0/kind-$(uname)-amd64 && chmod +x ./kind && sudo mv ./kind /usr/local/bin/kind\n\nkind version\n\n```\n\n> This command downloads the latest Kind binary.\n> Verify the upgrade by checking the Kind version.",
        "commands": [
          "curl -Lo ./kind https://kind.sigs.k8s.io/dl/v0.31.0/kind-$(uname)-amd64 && chmod +x ./kind && sudo mv ./kind /usr/local/bin/kind",
          "kind version"
        ]
      }
    ],
    "troubleshooting": [
      {
        "title": "Error: 'kind: command not found'",
        "description": "**Cause:** The Kind binary is not in your PATH.\n\n**Fix:**\nEnsure that the directory containing the Kind binary is added to your PATH."
      },
      {
        "title": "Error: 'Failed to create cluster: failed to start nodes'",
        "description": "**Cause:** Docker may not be running or there are insufficient resources.\n\n**Fix:**\nStart Docker and ensure you have enough resources allocated (minimum 2 vCPU, 4GB RAM)."
      },
      {
        "title": "Error: 'Failed to connect to the cluster'",
        "description": "**Cause:** The Kubernetes cluster may not be running.\n\n**Fix:**\nRun 'kind get clusters' to check the status of your clusters."
      },
      {
        "title": "Error: 'Image not found'",
        "description": "**Cause:** The specified Kubernetes version image is not available.\n\n**Fix:**\nEnsure you are using a valid Kubernetes version in the 'kind create cluster' command."
      }
    ],
    "versionNotes": [
      {
        "version": "v0.31.0",
        "changes": "Added support for Kubernetes 1.31, improved error messages during cluster creation.",
        "deprecations": "None.",
        "migrationSteps": "No specific migration steps required for this version."
      }
    ],
    "resolution": {
      "summary": "You should see output similar to 'NAME                 STATUS   ROLES    AGE   VERSION' with the nodes listed and their statuses as 'Ready'.",
      "codeSnippets": [
        "sudo apt-get update && sudo apt-get install -y docker.io",
        "brew install --cask docker",
        "[ $(uname -m) = x86_64 ] && curl -Lo ./kind https://kind.sigs.k8s.io/dl/v0.31.0/kind-$(uname)-amd64 && chmod +x ./kind && sudo mv ./kind /usr/local/bin/kind",
        "[ $(uname -m) = aarch64 ] && curl -Lo ./kind https://kind.sigs.k8s.io/dl/v0.31.0/kind-$(uname)-arm64 && chmod +x ./kind && sudo mv ./kind /usr/local/bin/kind",
        "kind create cluster --image kindest/node:v1.31.0",
        "kubectl get nodes"
      ]
    }
  },
  "metadata": {
    "tags": [
      "installation",
      "configuration",
      "local",
      "local-dev",
      "kubernetes-sig"
    ],
    "platform": "kind",
    "platformType": "local",
    "platformProvider": "Kubernetes SIG",
    "platformVersions": [
      "v0.31.0"
    ],
    "supportedK8sVersions": [
      "1.29",
      "1.30",
      "1.31"
    ],
    "cncfProjects": [],
    "targetResourceKinds": [
      "Namespace",
      "Deployment",
      "Service"
    ],
    "difficulty": "beginner",
    "issueTypes": [
      "installation",
      "configuration"
    ],
    "installMethods": [
      "cli"
    ],
    "containerImages": [
      "kindest/node:v1.31.0"
    ],
    "sourceUrls": {
      "docs": "https://kind.sigs.k8s.io/",
      "repo": "https://github.com/kubernetes-sigs/kind"
    },
    "qualityScore": 100
  },
  "prerequisites": {
    "kubernetes": "none",
    "tools": [
      "docker"
    ],
    "cloudCLI": "none",
    "resources": "Minimum 2 vCPU, 4GB RAM per node",
    "description": "Ensure Docker is installed and running before proceeding with Kind installation."
  },
  "security": {
    "scannedAt": "2026-04-03T06:26:01.916Z",
    "scannerVersion": "platform-install-gen-2.0.0",
    "sanitized": true,
    "findings": []
  }
}