{
  "version": "kc-mission-v1",
  "name": "consul-5231-consul-connect-ability-to-configure-envoy-access-log-path",
  "missionClass": "solution",
  "author": "KubeStellar Bot",
  "authorGithub": "kubestellar",
  "mission": {
    "title": "consul: Consul Connect - Ability to configure envoy access_log_path",
    "description": "Consul Connect - Ability to configure envoy access_log_path. Requested by 32+ users.",
    "type": "feature",
    "status": "completed",
    "steps": [
      {
        "title": "Check current consul deployment",
        "description": "Verify your consul version and configuration:\n```bash\nkubectl get pods -n consul -l app.kubernetes.io/name=consul\nhelm list -n consul 2>/dev/null || echo \"Not installed via Helm\"\n```\nThis feature requires a working consul installation."
      },
      {
        "title": "Review consul configuration",
        "description": "Inspect the relevant consul configuration:\n```bash\nkubectl get all -n consul -l app.kubernetes.io/name=consul\nkubectl get configmap -n consul -l app.kubernetes.io/part-of=consul\n```\n#### Feature Description\n\nThe access_log_path for Envoy currently defaults to /dev/null. It'd be great if this was configurable with Consul Connect.\n\n#### Use Case(s)\n\nOutput envoy access logs to stdout or saving them to a local file."
      },
      {
        "title": "Apply the fix for Consul Connect - Ability to configure envoy access_log_path",
        "description": "Reopening to capture that we want to be able to configure the access log path for both the TCPProxy filters and the HTTP Connect Manager within the xDS package in addition to the access logs for the admin interface.\n```yaml\nstatic_resources:\n  listeners:\n  - name: inbound_10000\n    address:\n      socket_address:\n        protocol: TCP\n        address: 0.0.0.0\n        port_value: 10000\n    traffic_direction: INBOUND\n    filter_chains:\n    - filters:\n      - name: envoy.filters.network.http_connection_manager\n        typed_config:\n          \"@type\": type.googleapis.com/envoy.config.filter.network.http_connection_manager.v2.HttpConnectionManager\n          access_log:\n          - name: envoy.access_loggers.file\n            config:\n              path: /dev/stdout\n```"
      },
      {
        "title": "Verify the feature works",
        "description": "Test that the new capability is working as expected:\n```bash\nkubectl get pods -n consul -l app.kubernetes.io/name=consul\nkubectl get events -n consul --sort-by='.lastTimestamp' | tail -10\n```\nConfirm the feature described in \"Consul Connect - Ability to configure envoy access_log_path\" is functioning correctly."
      }
    ],
    "resolution": {
      "summary": "Reopening to capture that we want to be able to configure the access log path for both the TCPProxy filters and the HTTP Connect Manager within the xDS package in addition to the access logs for the admin interface.",
      "codeSnippets": [
        "static_resources:\n  listeners:\n  - name: inbound_10000\n    address:\n      socket_address:\n        protocol: TCP\n        address: 0.0.0.0\n        port_value: 10000\n    traffic_direction: INBOUND\n    filter_chains:\n    - filters:\n      - name: envoy.filters.network.http_connection_manager\n        typed_config:\n          \"@type\": type.googleapis.com/envoy.config.filter.network.http_connection_manager.v2.HttpConnectionManager\n          access_log:\n          - name: envoy.access_loggers.file\n            config:\n              path: /dev/stdout",
        "envoy_public_listener_json= <<EOL\n             {\n                \"name\": \"local_agent\",\n                \"address\": {\n                  \"socket_address\": {\n                    \"address\": \"0.0.0.0\",\n\t\t\t\t\t\"port_value\": 20002\n                  }\n                },\n                \"filter_chains\": [\n                 {\n                   \"filters\": [\n                   {\n                     \"name\": \"envoy.tcp_proxy\",\n                     \"config\": {\n\t\t\t\t\t   \"cluster\": \"redis01\",\n                       \"stat_prefix\": \"envoy.tcp_proxy\",\n                     \"tracing\": {\n                       \"random_sampling\": {}\n                     },                     \n                    \"access_log\": {\n                      \"name\": \"envoy.file_access_log\",\n                      \"typed_config\": {\n         "
      ]
    }
  },
  "metadata": {
    "tags": [
      "consul",
      "community",
      "service-mesh",
      "feature"
    ],
    "cncfProjects": [
      "consul"
    ],
    "targetResourceKinds": [],
    "difficulty": "intermediate",
    "issueTypes": [
      "feature"
    ],
    "maturity": "community",
    "sourceUrls": {
      "issue": "https://github.com/hashicorp/consul/issues/5231",
      "repo": "https://github.com/hashicorp/consul",
      "pr": "https://github.com/hashicorp/consul/pull/5858"
    },
    "reactions": 32,
    "comments": 21,
    "synthesizedBy": "copilot"
  },
  "prerequisites": {
    "kubernetes": ">=1.24",
    "tools": [
      "kubectl"
    ],
    "description": "A running Kubernetes cluster with consul installed or the issue environment reproducible."
  },
  "security": {
    "scannedAt": "2026-03-15T06:50:21.813Z",
    "scannerVersion": "cncf-gen-3.0.0",
    "sanitized": true,
    "findings": []
  }
}
